omuplugin_emoji/__init__.py
omuplugin_emoji/plugin.py
omuplugin_emoji/version.py
omuplugin_emoji-0.9.24.dist-info/METADATA
omuplugin_emoji-0.9.24.dist-info/WHEEL
omuplugin_emoji-0.9.24.dist-info/entry_points.txt
omuplugin_emoji-0.9.24.dist-info/RECORD
